{"content_badminton_index.md":"C3WGyLZs","content_c_index.md":"CYmiYXAl","content_c_part1_index.md":"Dbtcheg3","content_c_part1_基础.md":"A7gAHWW8","content_c_part2_index.md":"xwls1DS2","content_c_part2_语法.md":"DH68tKxv","content_c_part3_index.md":"CYKrILKH","content_c_part4_index.md":"rex0kgiP","content_c_part5_index.md":"BhyRzCU3","content_c_part6_index.md":"DrlqGlHH","content_cpp_index.md":"wJ6eNBRF","content_electronic_index.md":"CaWub4qO","content_framework_index.md":"BQToCG7g","content_graphic_index.md":"B0-OHu82","content_java_index.md":"De3FuaVE","content_linux_index.md":"Dpms0JW0","content_project_index.md":"Crhqs20S","content_react_index.md":"D7yLnOXJ","content_runner_index.md":"Mh2fRgFb","content_rust_index.md":"DgEPPLVO","content_swift_index.md":"BfUiEj-S","index.md":"BHpfdfXZ","program.md":"hJ6ZQykm"}
